pgdeploy/__init__.py
pgdeploy/exceptions.py
pgdeploy/migration.py
pgdeploy/migrator.py
pgdeploy/schemas.py
pgdeploy-0.0.1.dist-info/DESCRIPTION.rst
pgdeploy-0.0.1.dist-info/METADATA
pgdeploy-0.0.1.dist-info/RECORD
pgdeploy-0.0.1.dist-info/WHEEL
pgdeploy-0.0.1.dist-info/metadata.json
pgdeploy-0.0.1.dist-info/top_level.txt
